sns_bridge/__init__.py
sns_bridge/chalice.py
sns_bridge/main.py
sns_bridge/sns.py
sns_bridge/wsgi.py
sns_bridge-0.1.1.dist-info/entry_points.txt
sns_bridge-0.1.1.dist-info/LICENSE
sns_bridge-0.1.1.dist-info/WHEEL
sns_bridge-0.1.1.dist-info/METADATA
sns_bridge-0.1.1.dist-info/RECORD
